l0/__init__.py
l0/_structured.py
l0/_utils.py
l0/adapters.py
l0/client.py
l0/comparison.py
l0/consensus.py
l0/continuation.py
l0/drift.py
l0/errors.py
l0/event_sourcing.py
l0/events.py
l0/format.py
l0/guardrails.py
l0/json_schema.py
l0/logging.py
l0/metrics.py
l0/multimodal.py
l0/normalize.py
l0/parallel.py
l0/pipeline.py
l0/pool.py
l0/py.typed
l0/retry.py
l0/runtime.py
l0/state.py
l0/state_machine.py
l0/stream.py
l0/types.py
l0/version.py
l0/window.py
l0/api/__init__.py
l0/api/adapters.py
l0/api/comparison.py
l0/api/consensus.py
l0/api/continuation.py
l0/api/core.py
l0/api/drift.py
l0/api/errors.py
l0/api/event_sourcing.py
l0/api/events.py
l0/api/format.py
l0/api/guardrails.py
l0/api/json.py
l0/api/json_schema.py
l0/api/logging.py
l0/api/metrics.py
l0/api/monitoring.py
l0/api/multimodal.py
l0/api/parallel.py
l0/api/pipeline.py
l0/api/pool.py
l0/api/state_machine.py
l0/api/structured.py
l0/api/text.py
l0/api/window.py
l0/eventsourcing/__init__.py
l0/eventsourcing/adapters.py
l0/eventsourcing/recorder.py
l0/eventsourcing/replayer.py
l0/eventsourcing/sourcing.py
l0/eventsourcing/store.py
l0/eventsourcing/types.py
l0/formatting/__init__.py
l0/formatting/context.py
l0/formatting/memory.py
l0/formatting/output.py
l0/formatting/strings.py
l0/formatting/tools.py
l0/monitoring/__init__.py
l0/monitoring/config.py
l0/monitoring/dispatcher.py
l0/monitoring/exporter.py
l0/monitoring/handlers.py
l0/monitoring/monitor.py
l0/monitoring/normalize.py
l0/monitoring/otel.py
l0/monitoring/sentry.py
l0/monitoring/telemetry.py
l0/pydantic/__init__.py
l0/pydantic/consensus.py
l0/pydantic/drift.py
l0/pydantic/errors.py
l0/pydantic/event_sourcing.py
l0/pydantic/events.py
l0/pydantic/guardrails.py
l0/pydantic/metrics.py
l0/pydantic/parallel.py
l0/pydantic/pipeline.py
l0/pydantic/pool.py
l0/pydantic/state_machine.py
l0/pydantic/types.py
l0/pydantic/window.py
ai2070_l0-0.19.0.dist-info/METADATA
ai2070_l0-0.19.0.dist-info/WHEEL
ai2070_l0-0.19.0.dist-info/licenses/LICENSE
ai2070_l0-0.19.0.dist-info/RECORD
