Metadata-Version: 2.4
Name: ai2070-l0
Version: 0.19.0
Summary: Reliability layer for AI/LLM streaming with retry, guardrails, and observability
Project-URL: Homepage, https://github.com/ai-2070/l0
Project-URL: Documentation, https://github.com/ai-2070/l0/tree/main/l0-python#readme
Project-URL: Repository, https://github.com/ai-2070/l0
Project-URL: Changelog, https://github.com/ai-2070/l0/releases
Project-URL: Issues, https://github.com/ai-2070/l0/issues
License: Apache-2.0
License-File: LICENSE
Keywords: ai,anthropic,fallback,guardrails,litellm,llm,observability,openai,reliability,resilience,retry,streaming,timeout
Classifier: Development Status :: 4 - Beta
Classifier: Intended Audience :: Developers
Classifier: License :: OSI Approved :: Apache Software License
Classifier: Programming Language :: Python :: 3
Classifier: Programming Language :: Python :: 3.10
Classifier: Programming Language :: Python :: 3.11
Classifier: Programming Language :: Python :: 3.12
Classifier: Programming Language :: Python :: 3.13
Classifier: Programming Language :: Python :: 3.14
Classifier: Topic :: Software Development :: Libraries :: Python Modules
Classifier: Typing :: Typed
Requires-Python: >=3.10
Requires-Dist: httpx>=0.27.0
Requires-Dist: orjson>=3.9.0
Requires-Dist: pydantic>=2.0.0
Requires-Dist: typing-extensions>=4.9.0
Requires-Dist: uuid6<2026,>=2024.1.12
Provides-Extra: litellm
Requires-Dist: litellm<2.0,>=1.40; extra == 'litellm'
Provides-Extra: observability
Requires-Dist: opentelemetry-api<2.0,>=1.20; extra == 'observability'
Requires-Dist: opentelemetry-instrumentation-httpx<1.0,>=0.45; extra == 'observability'
Requires-Dist: opentelemetry-sdk<2.0,>=1.20; extra == 'observability'
Requires-Dist: sentry-sdk<3.0,>=2.0; extra == 'observability'
Provides-Extra: openai
Requires-Dist: openai<3.0,>=2.0; extra == 'openai'
Provides-Extra: otel
Requires-Dist: opentelemetry-api<2.0,>=1.20; extra == 'otel'
Requires-Dist: opentelemetry-instrumentation-httpx<1.0,>=0.45; extra == 'otel'
Requires-Dist: opentelemetry-sdk<2.0,>=1.20; extra == 'otel'
Provides-Extra: sentry
Requires-Dist: sentry-sdk<3.0,>=2.0; extra == 'sentry'
Provides-Extra: speed
Requires-Dist: uvloop>=0.19; (platform_system != 'Windows') and extra == 'speed'
